nesterlist2017test.py
nesterlist2017test-1.1.0.dist-info/DESCRIPTION.rst
nesterlist2017test-1.1.0.dist-info/METADATA
nesterlist2017test-1.1.0.dist-info/RECORD
nesterlist2017test-1.1.0.dist-info/WHEEL
nesterlist2017test-1.1.0.dist-info/metadata.json
nesterlist2017test-1.1.0.dist-info/top_level.txt
