Metadata-Version: 2.0
Name: nesterlist2017test
Version: 1.1.0
Summary: A simple printer of nesterlist2017test
Home-page: UNKNOWN
Author: johnson
Author-email: 453713729@qq.com
License: UNKNOWN
Platform: UNKNOWN
